Geopy118ZhongwenWendang/README.md
Geopy118ZhongwenWendang/__init__.py
Geopy118ZhongwenWendang/__main__.py
Geopy118ZhongwenWendang/file.epub
Geopy118ZhongwenWendang/index.html
Geopy118ZhongwenWendang/css/__init__.py
Geopy118ZhongwenWendang/css/annotations.css
Geopy118ZhongwenWendang/css/main.css
Geopy118ZhongwenWendang/css/normalize.css
Geopy118ZhongwenWendang/css/popup.css
Geopy118ZhongwenWendang/font/__init__.py
Geopy118ZhongwenWendang/font/fontello.eot
Geopy118ZhongwenWendang/font/fontello.svg
Geopy118ZhongwenWendang/font/fontello.ttf
Geopy118ZhongwenWendang/font/fontello.woff
Geopy118ZhongwenWendang/img/__init__.py
Geopy118ZhongwenWendang/img/annotator-glyph-sprite.png
Geopy118ZhongwenWendang/img/annotator-icon-sprite.png
Geopy118ZhongwenWendang/img/apple-touch-icon.png
Geopy118ZhongwenWendang/img/cancelfullscreen.png
Geopy118ZhongwenWendang/img/close.png
Geopy118ZhongwenWendang/img/fullscreen.png
Geopy118ZhongwenWendang/img/loader.gif
Geopy118ZhongwenWendang/img/menu-icon.png
Geopy118ZhongwenWendang/img/save.png
Geopy118ZhongwenWendang/img/saved.png
Geopy118ZhongwenWendang/img/settings-s.png
Geopy118ZhongwenWendang/img/settings.png
Geopy118ZhongwenWendang/img/star.png
Geopy118ZhongwenWendang/js/__init__.py
Geopy118ZhongwenWendang/js/epub.js
Geopy118ZhongwenWendang/js/epub.min.js
Geopy118ZhongwenWendang/js/epub.min.map
Geopy118ZhongwenWendang/js/hooks.min.js
Geopy118ZhongwenWendang/js/hooks.min.map
Geopy118ZhongwenWendang/js/reader.js
Geopy118ZhongwenWendang/js/reader.js.map
Geopy118ZhongwenWendang/js/reader.min.js
Geopy118ZhongwenWendang/js/reader.min.map
Geopy118ZhongwenWendang/js/hooks/__init__.py
Geopy118ZhongwenWendang/js/hooks/extensions/__init__.py
Geopy118ZhongwenWendang/js/hooks/extensions/highlight.js
Geopy118ZhongwenWendang/js/libs/__init__.py
Geopy118ZhongwenWendang/js/libs/jquery.min.js
Geopy118ZhongwenWendang/js/libs/localforage.min.js
Geopy118ZhongwenWendang/js/libs/screenfull.js
Geopy118ZhongwenWendang/js/libs/screenfull.min.js
geopy_1_18_zhongwen_wendang-2024.3.5.0.dist-info/METADATA
geopy_1_18_zhongwen_wendang-2024.3.5.0.dist-info/WHEEL
geopy_1_18_zhongwen_wendang-2024.3.5.0.dist-info/entry_points.txt
geopy_1_18_zhongwen_wendang-2024.3.5.0.dist-info/top_level.txt
geopy_1_18_zhongwen_wendang-2024.3.5.0.dist-info/RECORD
